Metadata-Version: 2.1
Name: myCDEPS
Version: 1.0
Summary: A description of your package
Home-page: https://github.com/zeshidecode/CEDPS
Author: ze shi
Author-email: your.email@example.com
